LICENSE
README.md
setup.cfg
setup.py
pyLFDA/__init__.py
pyLFDA/pyLFDA.py
pyLFDA.egg-info/PKG-INFO
pyLFDA.egg-info/SOURCES.txt
pyLFDA.egg-info/dependency_links.txt
pyLFDA.egg-info/requires.txt
pyLFDA.egg-info/top_level.txt